{
    "filename": "IMG_9346_l7mnl29.png",
    "recognized_texts": [
        "LAUNDRY",
        "MANAGER"
    ],
    "symbol_definition": "인식된 기호 설명 없음",
    "ocr_raw_response": {
        "version": "V2",
        "requestId": "9539b6ab-e98f-4c07-94a2-315c46fdf211",
        "timestamp": 1754696885428,
        "images": [
            {
                "uid": "fe59ccaed77c477ab57a60b5cca06473",
                "name": "IMG_9346_l7mnl29.png",
                "inferResult": "SUCCESS",
                "message": "SUCCESS",
                "validationResult": {
                    "result": "NO_REQUESTED"
                },
                "convertedImageInfo": {
                    "width": 1024,
                    "height": 1024,
                    "pageIndex": 0,
                    "longImage": false
                },
                "fields": [
                    {
                        "valueType": "ALL",
                        "boundingPoly": {
                            "vertices": [
                                {
                                    "x": 299.0,
                                    "y": 703.0
                                },
                                {
                                    "x": 722.0,
                                    "y": 702.0
                                },
                                {
                                    "x": 722.0,
                                    "y": 768.0
                                },
                                {
                                    "x": 299.0,
                                    "y": 769.0
                                }
                            ]
                        },
                        "inferText": "LAUNDRY",
                        "inferConfidence": 1.0,
                        "type": "NORMAL",
                        "lineBreak": true
                    },
                    {
                        "valueType": "ALL",
                        "boundingPoly": {
                            "vertices": [
                                {
                                    "x": 384.0,
                                    "y": 786.0
                                },
                                {
                                    "x": 643.0,
                                    "y": 786.0
                                },
                                {
                                    "x": 643.0,
                                    "y": 824.0
                                },
                                {
                                    "x": 384.0,
                                    "y": 824.0
                                }
                            ]
                        },
                        "inferText": "MANAGER",
                        "inferConfidence": 1.0,
                        "type": "NORMAL",
                        "lineBreak": true
                    }
                ]
            }
        ]
    }
}